flask_yarn.py
setup.py
Flask_yarn.egg-info/PKG-INFO
Flask_yarn.egg-info/SOURCES.txt
Flask_yarn.egg-info/dependency_links.txt
Flask_yarn.egg-info/requires.txt
Flask_yarn.egg-info/top_level.txt
Flask_yarn.egg-info/zip-safe