Metadata-Version: 1.1
Name: Flask-yarn
Version: 1.0
Summary: serve yarn package with pretty
Home-page: https://github.com/lightsing/flask-yarn
Author: lightsing
Author-email: light.tsing@gmail.com
License: MIT
Platform: any
Classifier: Environment :: Web Environment
Classifier: Intended Audience :: Developers
Classifier: License :: OSI Approved :: MIT License
Classifier: Operating System :: OS Independent
Classifier: Programming Language :: Python
Classifier: Topic :: Internet :: WWW/HTTP :: Dynamic Content
Classifier: Topic :: Software Development :: Libraries :: Python Modules
